macrostrat/app_frame/__init__.py
macrostrat/app_frame/compose/__init__.py
macrostrat/app_frame/compose/base.py
macrostrat/app_frame/compose/follow_logs.py
macrostrat/app_frame/control_command.py
macrostrat/app_frame/core.py
macrostrat/app_frame/exc.py
macrostrat/app_frame/subsystems/__init__.py
macrostrat/app_frame/subsystems/defs.py
macrostrat/app_frame/utils/__init__.py
test_app/Caddyfile
test_app/__init__.py
test_app/docker-compose.yaml
macrostrat_app_frame-2.2.0.dist-info/METADATA
macrostrat_app_frame-2.2.0.dist-info/WHEEL
macrostrat_app_frame-2.2.0.dist-info/entry_points.txt
macrostrat_app_frame-2.2.0.dist-info/RECORD
