Metadata-Version: 2.1
Name: macrostrat.app_frame
Version: 2.2.0
Summary: A control script framework for containerized applications.
Author: Daven Quinn
Author-email: dev@davenquinn.com
Requires-Python: >=3.10,<4.0
Classifier: Programming Language :: Python :: 3
Classifier: Programming Language :: Python :: 3.10
Classifier: Programming Language :: Python :: 3.11
Classifier: Programming Language :: Python :: 3.12
Requires-Dist: macrostrat.utils (>=1.3.0,<2.0.0)
Requires-Dist: packaging (>=24.1,<25.0)
Requires-Dist: python-dotenv (>=1.0.0,<2.0.0)
Requires-Dist: rich (>=13,<14)
Requires-Dist: toposort (>=1.5,<2.0)
Requires-Dist: typer (>=0.12.5,<0.13.0)
